{
  "users": [
    {
      "name": "Dr. Benny Schaefer",
      "id": 1
    },
    {
      "name": "Viola Zboncak",
      "id": 2
    },
    {
      "name": "Ms. Shawna Metz",
      "id": 3
    },
    {
      "name": "Geraldine Reinger",
      "id": 4
    },
    {
      "name": "Mrs. Maryann Robel",
      "id": 5
    }
  ],
  "albums": [
    {
      "userId": "2",
      "title": "Ergonomic Cotton Ball",
      "id": 10
    },
    {
      "userId": "2",
      "title": "Sleek Rubber Tuna",
      "id": 11
    },
    {
      "userId": 2,
      "title": "Incredible Plastic Tuna",
      "id": 12
    },
    {
      "userId": 2,
      "title": "Oriental Frozen Cheese",
      "id": 13
    },
    {
      "userId": 3,
      "title": "Small Concrete Pizza",
      "id": 14
    },
    {
      "userId": 3,
      "title": "Awesome Cotton Soap",
      "id": 15
    },
    {
      "userId": 1,
      "title": "Generic Wooden Car",
      "id": 17
    },
    {
      "userId": 1,
      "title": "Generic Concrete Soap",
      "id": 18
    },
    {
      "userId": 1,
      "title": "Electronic Soft Ball",
      "id": 19
    },
    {
      "userId": 1,
      "title": "Licensed Bronze Pants",
      "id": 20
    },
    {
      "userId": 4,
      "title": "Electronic Soft Fish",
      "id": 21
    }
  ],
  "photos": []
}